{
  "date": "2026-07-12 10:39",
  "source": "local",
  "total": 3388,
  "prev_total": 3373,
  "new_count": 193,
  "removed_count": 178,
  "elapsed_min": 32,
  "failed_sources": [
    "ftakken_fukuoka"
  ],
  "failed_steps": [
    "qa_gate",
    "deploy"
  ],
  "failure_details": [
    {
      "step": "qa_gate",
      "label": "qa_gate",
      "impact": "詳細不明",
      "stderr_tail": "\n[FAIL] minpaku-fukuoka.html:;   ✗ 掲載開始ヘッダー (first-seen-header): '掲載開始' not found; \n[FAIL] minpaku-osaka.html:",
      "reason": "エラー",
      "fix": "エラーログを確認"
    },
    {
      "step": "deploy",
      "label": "デプロイ",
      "impact": "レポートが公開されていない",
      "stderr_tail": "QA Gate blocked deploy",
      "reason": "エラー",
      "fix": "エラーログを確認"
    },
    {
      "step": "source_degraded:ftakken_fukuoka",
      "label": "ftakken_fukuoka（取得件数が急減）",
      "impact": "前回比>70%減 — diff計算から除外（サイト側の一時障害 or セレクタ変化の疑い）",
      "reason": "source_degraded",
      "stderr_tail": "ソース ftakken_fukuoka がフォールバック動作中。スクレイパーはOKだが取得件数が急減し、差分計算から自動除外された。",
      "fix": "1) サイトUIの変化を確認（セレクタ更新） 2) 一時障害なら翌日自動回復 3) 無視=ホワイトリスト追加"
    }
  ],
  "step_count": 24,
  "ok_count": 22,
  "step_status": {
    "search_suumo.py (osaka)": {
      "last_failure_at": "2026-07-06T04:41:35",
      "last_success_at": "2026-07-12T11:12:21"
    },
    "search_suumo.py (fukuoka)": {
      "last_failure_at": "2026-07-06T04:41:35",
      "last_success_at": "2026-07-12T11:12:21"
    },
    "search_suumo.py (tokyo)": {
      "last_failure_at": "2026-07-06T04:41:35",
      "last_success_at": "2026-07-12T11:12:21"
    },
    "search_multi_site.py": {
      "last_success_at": "2026-07-12T11:12:21",
      "last_failure_at": "2026-06-26T16:17:19"
    },
    "search_restate.py": {
      "last_success_at": "2026-07-12T11:12:21"
    },
    "search_ftakken.py --mode kubun": {
      "last_success_at": "2026-07-12T11:12:21",
      "last_failure_at": "2026-06-28T07:32:46"
    },
    "search_ftakken.py --mode ittomono": {
      "last_success_at": "2026-07-12T11:12:21",
      "last_failure_at": "2026-06-28T07:32:46"
    },
    "search_ftakken.py --mode budget": {
      "last_success_at": "2026-07-12T11:12:21",
      "last_failure_at": "2026-06-28T07:32:46"
    },
    "search_lifull.py": {
      "last_success_at": "2026-07-12T11:12:21",
      "last_failure_at": "2026-07-08T14:21:22"
    },
    "search_ittomono.py": {
      "last_success_at": "2026-07-12T11:12:21"
    },
    "search_yield_focused.py": {
      "last_success_at": "2026-07-12T11:12:21",
      "last_failure_at": "2026-07-07T09:05:45"
    },
    "enrich_maintenance.py": {
      "last_success_at": "2026-07-12T11:12:21",
      "last_failure_at": "2026-07-01T05:46:16"
    },
    "first_seen": {
      "last_success_at": "2026-07-12T11:12:21"
    },
    "url_check": {
      "last_success_at": "2026-07-12T11:12:21"
    },
    "generate_osaka_report.py": {
      "last_success_at": "2026-07-12T11:12:21",
      "last_failure_at": "2026-07-10T07:44:54"
    },
    "generate_fukuoka_report.py": {
      "last_success_at": "2026-07-12T11:12:21",
      "last_failure_at": "2026-07-10T07:44:54"
    },
    "generate_tokyo_report.py": {
      "last_success_at": "2026-07-12T11:12:21",
      "last_failure_at": "2026-07-10T07:44:54"
    },
    "generate_ittomono_report.py": {
      "last_success_at": "2026-07-12T11:12:21",
      "last_failure_at": "2026-07-10T07:44:54"
    },
    "generate_inquiry_messages.py": {
      "last_success_at": "2026-07-08T14:21:22",
      "last_failure_at": "2026-07-10T07:44:54"
    },
    "generate_market.py": {
      "last_success_at": "2026-07-12T11:12:21",
      "last_failure_at": "2026-07-10T07:44:54"
    },
    "write_hub_summary.py": {
      "last_failure_at": "2026-06-14T11:37:19",
      "last_success_at": "2026-07-12T11:12:21"
    },
    "pipeline_flag": {
      "last_failure_at": "2026-07-10T07:44:54",
      "last_success_at": "2026-07-08T14:21:22"
    },
    "pipeline_lifecycle": {
      "last_failure_at": "2026-06-14T11:37:19",
      "last_success_at": "2026-07-10T07:44:54"
    },
    "generate_market_post_sweep": {
      "last_success_at": "2026-07-08T14:21:22",
      "last_failure_at": "2026-07-10T07:44:54"
    },
    "pipeline_dashboard": {
      "last_failure_at": "2026-07-10T07:44:54",
      "last_success_at": "2026-07-08T14:21:22"
    },
    "naiken_analysis": {
      "last_failure_at": "2026-07-10T07:44:54",
      "last_success_at": "2026-07-08T14:21:22"
    },
    "qa_gate": {
      "last_success_at": "2026-07-10T07:44:54",
      "last_failure_at": "2026-07-12T11:12:21"
    },
    "deploy": {
      "last_success_at": "2026-07-10T07:44:54",
      "last_failure_at": "2026-07-12T11:12:21"
    },
    "count_anomaly_check": {
      "last_failure_at": "2026-07-08T14:21:22"
    },
    "search_suumo.py osaka --mode kodate": {
      "last_success_at": "2026-07-12T11:12:21"
    },
    "generate_investment_priority.py": {
      "last_success_at": "2026-07-12T11:12:21"
    }
  },
  "new_items": [
    {
      "name": "物件画像",
      "price_text": "3690万円",
      "price_man": 3690,
      "source": "yahoo_fukuoka"
    },
    {
      "name": "物件画像",
      "price_text": "2790万円",
      "price_man": 2790,
      "source": "yahoo_fukuoka"
    },
    {
      "name": "物件画像",
      "price_text": "2790万円",
      "price_man": 2790,
      "source": "yahoo_fukuoka"
    },
    {
      "name": "物件画像",
      "price_text": "2980万円",
      "price_man": 2980,
      "source": "yahoo_fukuoka"
    },
    {
      "name": "物件画像",
      "price_text": "3190万円",
      "price_man": 3190,
      "source": "multi_site_osaka"
    },
    {
      "name": "物件画像",
      "price_text": "3880万円",
      "price_man": 3880,
      "source": "yahoo_tokyo"
    },
    {
      "name": "サンポートハイツ",
      "price_text": "2690万円",
      "price_man": 2690,
      "source": "yahoo_fukuoka"
    },
    {
      "name": "サンポートハイツ　中古マンション",
      "price_text": "2690万円",
      "price_man": 2690,
      "source": "suumo_fukuoka"
    },
    {
      "name": "エステートマンション赤坂けやき通り",
      "price_text": "3880万円",
      "price_man": 3880,
      "source": "suumo_fukuoka"
    },
    {
      "name": "サンポートハイツ",
      "price_text": "2690万円",
      "price_man": 2690,
      "source": "suumo_fukuoka"
    },
    {
      "name": "第三住吉ハイツ",
      "price_text": "2549万円",
      "price_man": 2549,
      "source": "suumo_fukuoka"
    },
    {
      "name": "ネストピア博多グランドステージⅢ",
      "price_text": "4780万円",
      "price_man": 4780,
      "source": "suumo_fukuoka"
    },
    {
      "name": "アプローズ那珂",
      "price_text": "2880万円",
      "price_man": 2880,
      "source": "suumo_fukuoka"
    },
    {
      "name": "ベルアージュ井尻",
      "price_text": "2690万円",
      "price_man": 2690,
      "source": "suumo_fukuoka"
    },
    {
      "name": "ふよう港ハイツ【担当：中尾】　までお気軽にお問合せく…",
      "price_text": "2890万円",
      "price_man": 2890,
      "source": "suumo_fukuoka"
    },
    {
      "name": "ファミール南福岡",
      "price_text": "2680万円",
      "price_man": 2680,
      "source": "suumo_fukuoka"
    },
    {
      "name": "ふよう港ハイツ",
      "price_text": "2890万円",
      "price_man": 2890,
      "source": "suumo_fukuoka"
    },
    {
      "name": "サンシティ博多ｆｌｅｘ２１",
      "price_text": "3680万円",
      "price_man": 3680,
      "source": "suumo_fukuoka"
    },
    {
      "name": "ブライトクロス博多 SOUTH",
      "price_text": "3999万円",
      "price_man": 3999,
      "source": "suumo_fukuoka"
    },
    {
      "name": "アルファライフ博多プレシャス",
      "price_text": "4699万円",
      "price_man": 4699,
      "source": "suumo_fukuoka"
    },
    {
      "name": "ベルアージュ井尻",
      "price_text": "2690万円",
      "price_man": 2690,
      "source": "suumo_fukuoka"
    },
    {
      "name": "アルファライフ博多プレシャス",
      "price_text": "4599万円",
      "price_man": 4599,
      "source": "suumo_fukuoka"
    },
    {
      "name": "サヴォィ　ザ・リバーテラス",
      "price_text": "4599万円",
      "price_man": 4599,
      "source": "suumo_fukuoka"
    },
    {
      "name": "アーサー大橋エクシオ2",
      "price_text": "3790万円",
      "price_man": 3790,
      "source": "suumo_fukuoka"
    },
    {
      "name": "ロワールマンションやよい坂",
      "price_text": "1680万円",
      "price_man": 1680,
      "source": "suumo_fukuoka"
    },
    {
      "name": "アンピール長住2",
      "price_text": "2780万円",
      "price_man": 2780,
      "source": "suumo_fukuoka"
    },
    {
      "name": "フジハイム谷町",
      "price_text": "2999万円",
      "price_man": 2999,
      "source": "suumo_osaka"
    },
    {
      "name": "フジハイム谷町",
      "price_text": "2999万円",
      "price_man": 2999,
      "source": "suumo_osaka"
    },
    {
      "name": "フジハイム谷町",
      "price_text": "2999万円",
      "price_man": 2999,
      "source": "suumo_osaka"
    },
    {
      "name": "プレサンス心斎橋リベルタ",
      "price_text": "4380万円",
      "price_man": 4380,
      "source": "suumo_osaka"
    },
    {
      "name": "ユニライフ福島C棟　１階庭付き",
      "price_text": "3480万円",
      "price_man": 3480,
      "source": "suumo_osaka"
    },
    {
      "name": "藤和堂島ハイタウン",
      "price_text": "4290万円",
      "price_man": 4290,
      "source": "suumo_osaka"
    },
    {
      "name": "大淀セントポリア",
      "price_text": "2998万円",
      "price_man": 2998,
      "source": "suumo_osaka"
    },
    {
      "name": "日商岩井中津マンション",
      "price_text": "3999万円",
      "price_man": 3999,
      "source": "suumo_osaka"
    },
    {
      "name": "プレサンス天満橋アンジェ",
      "price_text": "4580万円",
      "price_man": 4580,
      "source": "suumo_osaka"
    },
    {
      "name": "シーズ梅田東",
      "price_text": "3180万円",
      "price_man": 3180,
      "source": "suumo_osaka"
    },
    {
      "name": "パラシオ北梅田",
      "price_text": "4798万円",
      "price_man": 4798,
      "source": "suumo_osaka"
    },
    {
      "name": "ローレルハイツ北天満2号棟",
      "price_text": "4180万円",
      "price_man": 4180,
      "source": "suumo_osaka"
    },
    {
      "name": "ノア天満",
      "price_text": "3180万円",
      "price_man": 3180,
      "source": "suumo_osaka"
    },
    {
      "name": "メゾン北梅田",
      "price_text": "3499万円",
      "price_man": 3499,
      "source": "suumo_osaka"
    },
    {
      "name": "リバーサイドほんじょう",
      "price_text": "2680万円",
      "price_man": 2680,
      "source": "suumo_osaka"
    },
    {
      "name": "ビーバードルチェ阿波座",
      "price_text": "1980万円",
      "price_man": 1980,
      "source": "suumo_osaka"
    },
    {
      "name": "エスリードOSAKA　MID　WEST",
      "price_text": "4280万円",
      "price_man": 4280,
      "source": "suumo_osaka"
    },
    {
      "name": "ダイドーメゾン大阪・中之島",
      "price_text": "4740万円",
      "price_man": 4740,
      "source": "suumo_osaka"
    },
    {
      "name": "本町セントラルハイツ",
      "price_text": "3980万円",
      "price_man": 3980,
      "source": "suumo_osaka"
    },
    {
      "name": "ノバカネイチ阿波座二番館",
      "price_text": "3090万円",
      "price_man": 3090,
      "source": "suumo_osaka"
    },
    {
      "name": "ワコー千石マンション",
      "price_text": "4798万円",
      "price_man": 4798,
      "source": "suumo_tokyo"
    },
    {
      "name": "■■ワコー護国寺マンション■■",
      "price_text": "4999万円",
      "price_man": 4999,
      "source": "suumo_tokyo"
    },
    {
      "name": "パシフィック自由ケ丘マンション",
      "price_text": "4499万円",
      "price_man": 4499,
      "source": "suumo_tokyo"
    },
    {
      "name": "中野弥生エコーハイツ",
      "price_text": "4180万円",
      "price_man": 4180,
      "source": "suumo_tokyo"
    },
    {
      "name": "岡本マンション",
      "price_text": "2780万円",
      "price_man": 2780,
      "source": "suumo_tokyo"
    },
    {
      "name": "光栄ハイツ",
      "price_text": "2280万円",
      "price_man": 2280,
      "source": "suumo_tokyo"
    },
    {
      "name": "スターパレス北品川",
      "price_text": "4280万円",
      "price_man": 4280,
      "source": "suumo_tokyo"
    },
    {
      "name": "ドルメン五反田",
      "price_text": "4499万円",
      "price_man": 4499,
      "source": "suumo_tokyo"
    },
    {
      "name": "ハイライフ大崎",
      "price_text": "4799万円",
      "price_man": 4799,
      "source": "suumo_tokyo"
    },
    {
      "name": "ライオンズマンション西早稲田桔梗",
      "price_text": "3980万円",
      "price_man": 3980,
      "source": "suumo_tokyo"
    },
    {
      "name": "シーアイマンションあずま百樹園",
      "price_text": "4580万円",
      "price_man": 4580,
      "source": "suumo_tokyo"
    },
    {
      "name": "朝日プラザ八広",
      "price_text": "3480万円",
      "price_man": 3480,
      "source": "suumo_tokyo"
    },
    {
      "name": "パシフィックパレス錦糸町",
      "price_text": "4980万円",
      "price_man": 4980,
      "source": "suumo_tokyo"
    },
    {
      "name": "朝日言問マンション902号室",
      "price_text": "4999万円",
      "price_man": 4999,
      "source": "suumo_tokyo"
    },
    {
      "name": "■□■ クレド・ハイツリー両国 ■□■ ～ 両国駅7…",
      "price_text": "4199万円",
      "price_man": 4199,
      "source": "suumo_tokyo"
    },
    {
      "name": "■□■ 朝日言問マンション ■□■ ～ 複数駅路線利…",
      "price_text": "4999万円",
      "price_man": 4999,
      "source": "suumo_tokyo"
    },
    {
      "name": "■□■ ハイツ両国駅前 ■□■ ～ 両国駅2分・新規…",
      "price_text": "4790万円",
      "price_man": 4790,
      "source": "suumo_tokyo"
    },
    {
      "name": "マンション宮",
      "price_text": "4180万円",
      "price_man": 4180,
      "source": "suumo_tokyo"
    },
    {
      "name": "ライジングプレイス浅草弐番館",
      "price_text": "4980万円",
      "price_man": 4980,
      "source": "suumo_tokyo"
    },
    {
      "name": "ライジングプレイス浅草弐番館",
      "price_text": "4980万円",
      "price_man": 4980,
      "source": "suumo_tokyo"
    },
    {
      "name": "エスポワール入谷",
      "price_text": "3980万円",
      "price_man": 3980,
      "source": "suumo_tokyo"
    },
    {
      "name": "■□■ 下谷第2サマリアマンション ■□■ ～ 複数…",
      "price_text": "2999万円",
      "price_man": 2999,
      "source": "suumo_tokyo"
    },
    {
      "name": "■□■ VILLEVIO MINOWA ■□■ ～三…",
      "price_text": "4998万円",
      "price_man": 4998,
      "source": "suumo_tokyo"
    },
    {
      "name": "■□■ 浅草ロイヤルマンション ■□■ ～ 浅草駅徒…",
      "price_text": "3998万円",
      "price_man": 3998,
      "source": "suumo_tokyo"
    },
    {
      "name": "健美家 福岡市南区井尻4-4#1lmv",
      "price_text": "0億8300万円",
      "price_man": 8300,
      "source": "ittomono_fukuoka"
    },
    {
      "name": "健美家 練馬区東大泉6-38#6rbt",
      "price_text": "1億4990万円",
      "price_man": 14990,
      "source": "ittomono_tokyo"
    },
    {
      "name": "健美家 練馬区北町5丁目10#9wxp",
      "price_text": "2億円",
      "price_man": 20000,
      "source": "ittomono_tokyo"
    },
    {
      "name": "M-Style坂下",
      "price_text": "1億2900万円",
      "price_man": 12900,
      "source": "ittomono_tokyo"
    },
    {
      "name": "東京都北区 一棟売りマンション",
      "price_text": "2億9000万円",
      "price_man": 29000,
      "source": "ittomono_tokyo"
    },
    {
      "name": "ハコビル",
      "price_text": "1億9500万円",
      "price_man": 19500,
      "source": "ittomono_tokyo"
    },
    {
      "name": "【利回り１０％】和泉市・北信太駅■大規模マンション",
      "price_text": "2899万円",
      "price_man": 2899,
      "source": "yield_osaka"
    },
    {
      "name": "桜川駅徒歩５分のオーナーチェンジ物件",
      "price_text": "1500万円",
      "price_man": 1500,
      "source": "yield_osaka"
    },
    {
      "name": "天満駅徒歩３分のオーナーチェンジ物件",
      "price_text": "1980万円",
      "price_man": 1980,
      "source": "yield_osaka"
    },
    {
      "name": "南港中■大規模マンション■室内リフォーム済み",
      "price_text": "1950万円",
      "price_man": 1950,
      "source": "yield_osaka"
    },
    {
      "name": "アドバンス大阪城レガーレ",
      "price_text": "1500万円",
      "price_man": 1500,
      "source": "yield_osaka"
    },
    {
      "name": "【肥後橋8分】平成27年・賃貸中・1840万円・4.56％",
      "price_text": "1840万円",
      "price_man": 1840,
      "source": "yield_osaka"
    },
    {
      "name": "お買い物に困らない便利なエリアです！",
      "price_text": "2500万円",
      "price_man": 2500,
      "source": "yield_osaka"
    },
    {
      "name": "【中津8分】平成27年・賃貸中・1890万円・4.44％",
      "price_text": "1890万円",
      "price_man": 1890,
      "source": "yield_osaka"
    },
    {
      "name": "防音性が高く生活音が気にならず、共用部分や自転車置き場も綺麗",
      "price_text": "1780万円",
      "price_man": 1780,
      "source": "yield_osaka"
    },
    {
      "name": "防音性が高く静かで、住人も落ち着いた雰囲気の物件",
      "price_text": "1900万円",
      "price_man": 1900,
      "source": "yield_osaka"
    },
    {
      "name": "ライオンズマンション西長堀◇上層階角部屋◇約35㎡",
      "price_text": "1480万円",
      "price_man": 1480,
      "source": "yield_osaka"
    },
    {
      "name": "ライオンズマンション西長堀◇上層階角部屋◇約35㎡",
      "price_text": "670万円",
      "price_man": 670,
      "source": "yield_osaka"
    },
    {
      "name": "堺筋本町駅徒歩3分のオーナーチェンジ物件",
      "price_text": "2400万円",
      "price_man": 2400,
      "source": "yield_osaka"
    },
    {
      "name": "9駅8路線利用可能な都心の築浅ペット可物件！",
      "price_text": "2280万円",
      "price_man": 2280,
      "source": "yield_osaka"
    },
    {
      "name": "今宮戎駅徒歩１分のオーナーチェンジ物件",
      "price_text": "1670万円",
      "price_man": 1670,
      "source": "yield_osaka"
    },
    {
      "name": "【天満橋5分】平成23年・賃貸中・1840万円・4.43％",
      "price_text": "1840万円",
      "price_man": 1840,
      "source": "yield_osaka"
    },
    {
      "name": "【堺筋本町2分】平成20年・賃貸中・2080万円・4.44％",
      "price_text": "2080万円",
      "price_man": 2080,
      "source": "yield_osaka"
    },
    {
      "name": "本町アーバンライフ",
      "price_text": "1190万円",
      "price_man": 1190,
      "source": "yield_osaka"
    },
    {
      "name": "エイペックス梅田東Ⅱ",
      "price_text": "2400万円",
      "price_man": 2400,
      "source": "yield_osaka"
    },
    {
      "name": "エステムエグゼ心斎橋",
      "price_text": "5000万円",
      "price_man": 5000,
      "source": "rakumachi_osaka"
    },
    {
      "name": "ライオンズマンション中之島公園北",
      "price_text": "2380万円",
      "price_man": 2380,
      "source": "yield_osaka"
    },
    {
      "name": "東大島",
      "price_text": "7000万円",
      "price_man": 7000,
      "source": "yield_ittomono_tokyo"
    },
    {
      "name": "土地先行",
      "price_text": "7200万円",
      "price_man": 7200,
      "source": "yield_ittomono_tokyo"
    },
    {
      "name": "足立区南花畑",
      "price_text": "7000万円",
      "price_man": 7000,
      "source": "yield_ittomono_tokyo"
    },
    {
      "name": "幡ヶ谷",
      "price_text": "5200万円",
      "price_man": 5200,
      "source": "yield_ittomono_tokyo"
    },
    {
      "name": "品川区",
      "price_text": "2億円",
      "price_man": 20000,
      "source": "ittomono_tokyo"
    },
    {
      "name": "青梅街道駅歩6分！表面利回り約5.13%！オーナーチェンジ",
      "price_text": "7000万円",
      "price_man": 7000,
      "source": "yield_ittomono_tokyo"
    },
    {
      "name": "【新宿区】都営新宿線「曙橋」駅徒歩5分！【RC4階建】",
      "price_text": "1億6800万円",
      "price_man": 16800,
      "source": "ittomono_tokyo"
    },
    {
      "name": "【練馬区】西武池袋線「保谷」駅徒歩8分！",
      "price_text": "1億5000万円",
      "price_man": 15000,
      "source": "ittomono_tokyo"
    },
    {
      "name": "北区",
      "price_text": "2億880万円",
      "price_man": 20880,
      "source": "ittomono_tokyo"
    },
    {
      "name": "【全物件仲手1％（売却・購入）】",
      "price_text": "1億5000万円",
      "price_man": 15000,
      "source": "ittomono_tokyo"
    },
    {
      "name": "多摩市",
      "price_text": "6200万円",
      "price_man": 6200,
      "source": "yield_ittomono_tokyo"
    },
    {
      "name": "西武下井草駅徒歩10分◇2017年築アパート",
      "price_text": "5500万円",
      "price_man": 5500,
      "source": "yield_ittomono_tokyo"
    },
    {
      "name": "京成曳舟",
      "price_text": "8300万円",
      "price_man": 8300,
      "source": "ittomono_tokyo"
    },
    {
      "name": "中野区1棟アパート！融資相談受付中！中国語＆EngOK",
      "price_text": "5990万円",
      "price_man": 5990,
      "source": "yield_ittomono_tokyo"
    },
    {
      "name": "台東区柳橋二丁目アパート",
      "price_text": "7685万円",
      "price_man": 7685,
      "source": "yield_ittomono_tokyo"
    },
    {
      "name": "楽待 杉並区永福４丁目#1157",
      "price_text": "3300万円",
      "price_man": 3300,
      "source": "yield_ittomono_tokyo"
    },
    {
      "name": "ミリオンタワー虎ノ門【駅徒歩4分×管理体制良好】",
      "price_text": "1420万円",
      "price_man": 1420,
      "source": "yield_tokyo"
    },
    {
      "name": "▶三ノ輪駅徒歩8分！新耐震！賃貸中！",
      "price_text": "1050万円",
      "price_man": 1050,
      "source": "yield_tokyo"
    },
    {
      "name": "日本橋三越前アムフラット",
      "price_text": "1398万円",
      "price_man": 1398,
      "source": "yield_tokyo"
    },
    {
      "name": "ハイシティ中野",
      "price_text": "980万円",
      "price_man": 980,
      "source": "yield_tokyo"
    },
    {
      "name": "パークフィーネ南大沢４番館",
      "price_text": "2698万円",
      "price_man": 2698,
      "source": "yield_tokyo"
    },
    {
      "name": "オリエンタル千駄ヶ谷",
      "price_text": "1840万円",
      "price_man": 1840,
      "source": "yield_tokyo"
    },
    {
      "name": "港区安定需要【白金高輪駅】徒歩4分人気マンションシリーズ投資",
      "price_text": "2290万円",
      "price_man": 2290,
      "source": "yield_tokyo"
    },
    {
      "name": "Ｂｒｉｌｌｉａ銀座ｉｄ",
      "price_text": "2990万円",
      "price_man": 2990,
      "source": "yield_tokyo"
    },
    {
      "name": "【町田市】2021年内装フルリフォーム【#3705】",
      "price_text": "1200万円",
      "price_man": 1200,
      "source": "yield_tokyo"
    },
    {
      "name": "ペンギン幡ヶ谷",
      "price_text": "1280万円",
      "price_man": 1280,
      "source": "yield_tokyo"
    },
    {
      "name": "アデッソ新宿若松町",
      "price_text": "2700万円",
      "price_man": 2700,
      "source": "yield_tokyo"
    },
    {
      "name": "港区安定収入【麻布十番駅】徒歩6分普通借オーナーチェンジ物件",
      "price_text": "2900万円",
      "price_man": 2900,
      "source": "yield_tokyo"
    },
    {
      "name": "【江東区】45平米で幅広い需要【#3683】",
      "price_text": "1600万円",
      "price_man": 1600,
      "source": "yield_tokyo"
    },
    {
      "name": "麻布十番商店街や複数のコンビニが徒歩圏内と生活利便性",
      "price_text": "2500万円",
      "price_man": 2500,
      "source": "yield_tokyo"
    },
    {
      "name": "足立区",
      "price_text": "1680万円",
      "price_man": 1680,
      "source": "yield_tokyo"
    },
    {
      "name": "ダイアパレス",
      "price_text": "998万円",
      "price_man": 998,
      "source": "yield_tokyo"
    },
    {
      "name": "賃貸中で家賃収入が見込める区分マンション",
      "price_text": "998万円",
      "price_man": 998,
      "source": "yield_tokyo"
    },
    {
      "name": "練馬駅徒歩６分のオーナーチェンジ物件",
      "price_text": "2000万円",
      "price_man": 2000,
      "source": "yield_tokyo"
    },
    {
      "name": "スカイコート品川第６",
      "price_text": "2290万円",
      "price_man": 2290,
      "source": "yield_tokyo"
    },
    {
      "name": "トップ北千住",
      "price_text": "2050万円",
      "price_man": 2050,
      "source": "yield_tokyo"
    },
    {
      "name": "ニュー池尻マンション",
      "price_text": "1510万円",
      "price_man": 1510,
      "source": "yield_tokyo"
    },
    {
      "name": "ダイアパレス大山",
      "price_text": "2850万円",
      "price_man": 2850,
      "source": "yield_tokyo"
    },
    {
      "name": "アイル東京スカイツリー",
      "price_text": "2890万円",
      "price_man": 2890,
      "source": "yield_tokyo"
    },
    {
      "name": "クラスタ台東根岸",
      "price_text": "2700万円",
      "price_man": 2700,
      "source": "yield_tokyo"
    },
    {
      "name": "東京都江東区",
      "price_text": "2900万円",
      "price_man": 2900,
      "source": "yield_tokyo"
    },
    {
      "name": "カーサ第1宇喜田1号棟",
      "price_text": "1650万円",
      "price_man": 1650,
      "source": "yield_tokyo"
    },
    {
      "name": "ロアール井荻駅前",
      "price_text": "2580万円",
      "price_man": 2580,
      "source": "yield_tokyo"
    },
    {
      "name": "【新宿区タワーレジデンス】賃貸中・大久保駅3分の好立地",
      "price_text": "1750万円",
      "price_man": 1750,
      "source": "yield_tokyo"
    },
    {
      "name": "新宿フラワーハイホーム",
      "price_text": "1700万円",
      "price_man": 1700,
      "source": "yield_tokyo"
    },
    {
      "name": "日の出駅歩4分！港区海岸2丁目アドレス！",
      "price_text": "1490万円",
      "price_man": 1490,
      "source": "yield_tokyo"
    },
    {
      "name": "東大島駅8分のオーナーチェンジ物件",
      "price_text": "1830万円",
      "price_man": 1830,
      "source": "yield_tokyo"
    },
    {
      "name": "グランメール中井",
      "price_text": "2700万円",
      "price_man": 2700,
      "source": "yield_tokyo"
    },
    {
      "name": "【売主】ウィンシティー上野タワー",
      "price_text": "2950万円",
      "price_man": 2950,
      "source": "yield_tokyo"
    },
    {
      "name": "【売主】G・コンフォート大山山手通り",
      "price_text": "2880万円",
      "price_man": 2880,
      "source": "yield_tokyo"
    },
    {
      "name": "◆月々74,000円で賃貸中　駅徒歩2分　オーナーチェンジ◆",
      "price_text": "1680万円",
      "price_man": 1680,
      "source": "yield_tokyo"
    },
    {
      "name": "リバーサイドタウン木場南スカイハイツ",
      "price_text": "2750万円",
      "price_man": 2750,
      "source": "yield_tokyo"
    },
    {
      "name": "新宿エリアの賃貸中区分マンション",
      "price_text": "2080万円",
      "price_man": 2080,
      "source": "yield_tokyo"
    },
    {
      "name": "◆月々75,000円で賃貸中　駅徒歩3分　オーナーチェンジ◆",
      "price_text": "2230万円",
      "price_man": 2230,
      "source": "yield_tokyo"
    },
    {
      "name": "クロスエアタワー",
      "price_text": "2780万円",
      "price_man": 2780,
      "source": "yield_tokyo"
    },
    {
      "name": "◆月々83,000円で賃貸中　駅徒歩1分　オーナーチェンジ◆",
      "price_text": "2000万円",
      "price_man": 2000,
      "source": "yield_tokyo"
    },
    {
      "name": "【東急リバブル 専属】ライオンズマンション目黒不動前",
      "price_text": "1300万円",
      "price_man": 1300,
      "source": "yield_tokyo"
    },
    {
      "name": "加賀マンション",
      "price_text": "2940万円",
      "price_man": 2940,
      "source": "yield_tokyo"
    },
    {
      "name": "スカイコート田端",
      "price_text": "1530万円",
      "price_man": 1530,
      "source": "yield_tokyo"
    },
    {
      "name": "ライオンズステーションプラザ大島",
      "price_text": "1200万円",
      "price_man": 1200,
      "source": "yield_tokyo"
    },
    {
      "name": "スカイコート板橋五番館",
      "price_text": "2150万円",
      "price_man": 2150,
      "source": "yield_tokyo"
    },
    {
      "name": "賃貸中で家賃収入が見込める区分マンション",
      "price_text": "1980万円",
      "price_man": 1980,
      "source": "yield_tokyo"
    },
    {
      "name": "マートルコート東中野グラン",
      "price_text": "930万円",
      "price_man": 930,
      "source": "yield_tokyo"
    },
    {
      "name": "日神パレス永福町",
      "price_text": "1080万円",
      "price_man": 1080,
      "source": "yield_tokyo"
    },
    {
      "name": "日神パレス永福町",
      "price_text": "1580万円",
      "price_man": 1580,
      "source": "yield_tokyo"
    },
    {
      "name": "セントレー市ヶ谷　南向き　オートロック　エレベーター",
      "price_text": "1780万円",
      "price_man": 1780,
      "source": "yield_tokyo"
    },
    {
      "name": "アセンションアイディ浅草　2010年築　独立洗面台",
      "price_text": "2900万円",
      "price_man": 2900,
      "source": "yield_tokyo"
    },
    {
      "name": "パレ・ドール文京メトロプラザ第一",
      "price_text": "2640万円",
      "price_man": 2640,
      "source": "yield_tokyo"
    },
    {
      "name": "パレ・ドール文京メトロプラザ第一",
      "price_text": "2400万円",
      "price_man": 2400,
      "source": "yield_tokyo"
    },
    {
      "name": "メインステージ江戸川橋",
      "price_text": "1780万円",
      "price_man": 1780,
      "source": "yield_tokyo"
    },
    {
      "name": "ベルグレードＨＭ",
      "price_text": "2060万円",
      "price_man": 2060,
      "source": "yield_tokyo"
    },
    {
      "name": "レジオス市谷",
      "price_text": "2760万円",
      "price_man": 2760,
      "source": "yield_tokyo"
    },
    {
      "name": "■ ダイホープラザ千歳烏山Ａ棟 ■",
      "price_text": "850万円",
      "price_man": 850,
      "source": "yield_tokyo"
    },
    {
      "name": "■ 藤和シティスクエア練馬 ■",
      "price_text": "1360万円",
      "price_man": 1360,
      "source": "yield_tokyo"
    },
    {
      "name": "ウインベルソロ赤羽第三",
      "price_text": "790万円",
      "price_man": 790,
      "source": "yield_tokyo"
    },
    {
      "name": "エントピア第三荻窪",
      "price_text": "2480万円",
      "price_man": 2480,
      "source": "yield_tokyo"
    },
    {
      "name": "Ｎ・フラット",
      "price_text": "1180万円",
      "price_man": 1180,
      "source": "yield_tokyo"
    },
    {
      "name": "Ｎ・フラット",
      "price_text": "1500万円",
      "price_man": 1500,
      "source": "yield_tokyo"
    },
    {
      "name": "Ｎ・フラット",
      "price_text": "1140万円",
      "price_man": 1140,
      "source": "yield_tokyo"
    },
    {
      "name": "Ｎ・フラット",
      "price_text": "2880万円",
      "price_man": 2880,
      "source": "yield_tokyo"
    },
    {
      "name": "ライオンズマンション",
      "price_text": "1490万円",
      "price_man": 1490,
      "source": "yield_tokyo"
    },
    {
      "name": "楽待 台東区北上野2#1117",
      "price_text": "1250万円",
      "price_man": 1250,
      "source": "yield_tokyo"
    },
    {
      "name": "楽待 板橋区三園1#1139",
      "price_text": "630万円",
      "price_man": 630,
      "source": "yield_tokyo"
    },
    {
      "name": "西高島平ダイカンプラザ",
      "price_text": "2510万円",
      "price_man": 2510,
      "source": "yield_tokyo"
    },
    {
      "name": "メゾン・ド・ルソール",
      "price_text": "530万円",
      "price_man": 530,
      "source": "yield_fukuoka"
    },
    {
      "name": "エンクレスト呉服町",
      "price_text": "2380万円",
      "price_man": 2380,
      "source": "yield_fukuoka"
    },
    {
      "name": "■■■【福岡",
      "price_text": "1100万円",
      "price_man": 1100,
      "source": "yield_fukuoka"
    },
    {
      "name": "リベーラガーデンC棟（セントラルウエスト）",
      "price_text": "750万円",
      "price_man": 750,
      "source": "yield_fukuoka"
    },
    {
      "name": "西鉄天神大牟田線",
      "price_text": "730万円",
      "price_man": 730,
      "source": "yield_fukuoka"
    },
    {
      "name": "渡辺通駅",
      "price_text": "1980万円",
      "price_man": 1980,
      "source": "yield_fukuoka"
    },
    {
      "name": "レジデンシャルヒルズリバープレイス",
      "price_text": "1980万円",
      "price_man": 1980,
      "source": "yield_fukuoka"
    },
    {
      "name": "レジデンシャルヒルズリバープレイス",
      "price_text": "2680万円",
      "price_man": 2680,
      "source": "yield_fukuoka"
    },
    {
      "name": "ニューライフ西公園",
      "price_text": "720万円",
      "price_man": 720,
      "source": "yield_fukuoka"
    },
    {
      "name": "スカイ・クリエート天神南",
      "price_text": "680万円",
      "price_man": 680,
      "source": "yield_fukuoka"
    },
    {
      "name": "キャッスルマンション箱崎九大前",
      "price_text": "1380万円",
      "price_man": 1380,
      "source": "yield_fukuoka"
    },
    {
      "name": "サヴォイマキシマイズ博多ステーション",
      "price_text": "1580万円",
      "price_man": 1580,
      "source": "yield_fukuoka"
    }
  ],
  "removed_items": [
    {
      "source": "yahoo_fukuoka"
    },
    {
      "source": "yahoo_fukuoka"
    },
    {
      "source": "yahoo_fukuoka"
    },
    {
      "source": "multi_site_osaka"
    },
    {
      "source": "multi_site_osaka"
    },
    {
      "source": "yahoo_fukuoka"
    },
    {
      "source": "yahoo_fukuoka"
    },
    {
      "source": "multi_site_osaka"
    },
    {
      "source": "suumo_fukuoka"
    },
    {
      "source": "suumo_fukuoka"
    },
    {
      "source": "suumo_fukuoka"
    },
    {
      "source": "suumo_fukuoka"
    },
    {
      "source": "suumo_fukuoka"
    },
    {
      "source": "suumo_fukuoka"
    },
    {
      "source": "suumo_fukuoka"
    },
    {
      "source": "suumo_fukuoka"
    },
    {
      "source": "suumo_fukuoka"
    },
    {
      "source": "suumo_fukuoka"
    },
    {
      "source": "suumo_fukuoka"
    },
    {
      "source": "suumo_fukuoka"
    },
    {
      "source": "suumo_osaka"
    },
    {
      "source": "suumo_osaka"
    },
    {
      "source": "suumo_osaka"
    },
    {
      "source": "suumo_osaka"
    },
    {
      "source": "suumo_osaka"
    },
    {
      "source": "suumo_osaka"
    },
    {
      "source": "suumo_osaka"
    },
    {
      "source": "suumo_osaka"
    },
    {
      "source": "suumo_osaka"
    },
    {
      "source": "suumo_osaka"
    },
    {
      "source": "suumo_osaka"
    },
    {
      "source": "suumo_osaka"
    },
    {
      "source": "suumo_osaka"
    },
    {
      "source": "suumo_osaka"
    },
    {
      "source": "suumo_osaka"
    },
    {
      "source": "suumo_osaka"
    },
    {
      "source": "suumo_osaka"
    },
    {
      "source": "suumo_tokyo"
    },
    {
      "source": "suumo_tokyo"
    },
    {
      "source": "suumo_tokyo"
    },
    {
      "source": "suumo_tokyo"
    },
    {
      "source": "suumo_tokyo"
    },
    {
      "source": "suumo_tokyo"
    },
    {
      "source": "suumo_tokyo"
    },
    {
      "source": "suumo_tokyo"
    },
    {
      "source": "suumo_tokyo"
    },
    {
      "source": "suumo_tokyo"
    },
    {
      "source": "suumo_tokyo"
    },
    {
      "source": "suumo_tokyo"
    },
    {
      "source": "suumo_tokyo"
    },
    {
      "source": "suumo_tokyo"
    },
    {
      "source": "suumo_tokyo"
    },
    {
      "source": "suumo_tokyo"
    },
    {
      "source": "suumo_tokyo"
    },
    {
      "source": "suumo_tokyo"
    },
    {
      "source": "suumo_tokyo"
    },
    {
      "source": "suumo_tokyo"
    },
    {
      "source": "suumo_tokyo"
    },
    {
      "source": "suumo_tokyo"
    },
    {
      "source": "ittomono_tokyo"
    },
    {
      "source": "ittomono_tokyo"
    },
    {
      "source": "ittomono_osaka"
    },
    {
      "source": "ittomono_tokyo"
    },
    {
      "source": "ittomono_tokyo"
    },
    {
      "source": "ittomono_tokyo"
    },
    {
      "source": "ittomono_tokyo"
    },
    {
      "source": "ittomono_tokyo"
    },
    {
      "source": "yield_osaka"
    },
    {
      "source": "yield_osaka"
    },
    {
      "source": "yield_osaka"
    },
    {
      "source": "yield_osaka"
    },
    {
      "source": "yield_osaka"
    },
    {
      "source": "yield_osaka"
    },
    {
      "source": "yield_osaka"
    },
    {
      "source": "rakumachi_osaka"
    },
    {
      "source": "yield_osaka"
    },
    {
      "source": "yield_osaka"
    },
    {
      "source": "yield_osaka"
    },
    {
      "source": "yield_osaka"
    },
    {
      "source": "yield_osaka"
    },
    {
      "source": "yield_osaka"
    },
    {
      "source": "yield_osaka"
    },
    {
      "source": "yield_osaka"
    },
    {
      "source": "yield_osaka"
    },
    {
      "source": "yield_osaka"
    },
    {
      "source": "yield_osaka"
    },
    {
      "source": "yield_osaka"
    },
    {
      "source": "ittomono_tokyo"
    },
    {
      "source": "ittomono_tokyo"
    },
    {
      "source": "ittomono_tokyo"
    },
    {
      "source": "ittomono_tokyo"
    },
    {
      "source": "yield_ittomono_tokyo"
    },
    {
      "source": "yield_ittomono_tokyo"
    },
    {
      "source": "yield_ittomono_tokyo"
    },
    {
      "source": "yield_ittomono_tokyo"
    },
    {
      "source": "yield_ittomono_tokyo"
    },
    {
      "source": "yield_ittomono_tokyo"
    },
    {
      "source": "ittomono_tokyo"
    },
    {
      "source": "yield_ittomono_tokyo"
    },
    {
      "source": "yield_ittomono_tokyo"
    },
    {
      "source": "yield_ittomono_tokyo"
    },
    {
      "source": "yield_ittomono_tokyo"
    },
    {
      "source": "yield_tokyo"
    },
    {
      "source": "yield_tokyo"
    },
    {
      "source": "yield_tokyo"
    },
    {
      "source": "yield_tokyo"
    },
    {
      "source": "yield_tokyo"
    },
    {
      "source": "yield_tokyo"
    },
    {
      "source": "yield_tokyo"
    },
    {
      "source": "yield_tokyo"
    },
    {
      "source": "yield_tokyo"
    },
    {
      "source": "yield_tokyo"
    },
    {
      "source": "yield_tokyo"
    },
    {
      "source": "yield_tokyo"
    },
    {
      "source": "yield_tokyo"
    },
    {
      "source": "yield_tokyo"
    },
    {
      "source": "yield_tokyo"
    },
    {
      "source": "yield_tokyo"
    },
    {
      "source": "yield_tokyo"
    },
    {
      "source": "yield_tokyo"
    },
    {
      "source": "yield_tokyo"
    },
    {
      "source": "yield_tokyo"
    },
    {
      "source": "yield_tokyo"
    },
    {
      "source": "yield_tokyo"
    },
    {
      "source": "yield_tokyo"
    },
    {
      "source": "yield_tokyo"
    },
    {
      "source": "yield_tokyo"
    },
    {
      "source": "yield_tokyo"
    },
    {
      "source": "yield_tokyo"
    },
    {
      "source": "yield_tokyo"
    },
    {
      "source": "yield_tokyo"
    },
    {
      "source": "yield_tokyo"
    },
    {
      "source": "yield_tokyo"
    },
    {
      "source": "yield_tokyo"
    },
    {
      "source": "yield_tokyo"
    },
    {
      "source": "yield_tokyo"
    },
    {
      "source": "yield_tokyo"
    },
    {
      "source": "yield_tokyo"
    },
    {
      "source": "yield_tokyo"
    },
    {
      "source": "yield_tokyo"
    },
    {
      "source": "yield_tokyo"
    },
    {
      "source": "yield_tokyo"
    },
    {
      "source": "yield_tokyo"
    },
    {
      "source": "yield_tokyo"
    },
    {
      "source": "yield_tokyo"
    },
    {
      "source": "yield_tokyo"
    },
    {
      "source": "yield_tokyo"
    },
    {
      "source": "yield_tokyo"
    },
    {
      "source": "yield_tokyo"
    },
    {
      "source": "yield_tokyo"
    },
    {
      "source": "yield_tokyo"
    },
    {
      "source": "yield_tokyo"
    },
    {
      "source": "yield_tokyo"
    },
    {
      "source": "yield_tokyo"
    },
    {
      "source": "yield_tokyo"
    },
    {
      "source": "yield_tokyo"
    },
    {
      "source": "yield_tokyo"
    },
    {
      "source": "yield_tokyo"
    },
    {
      "source": "yield_tokyo"
    },
    {
      "source": "yield_tokyo"
    },
    {
      "source": "yield_tokyo"
    },
    {
      "source": "yield_tokyo"
    },
    {
      "source": "yield_tokyo"
    },
    {
      "source": "yield_tokyo"
    },
    {
      "source": "yield_tokyo"
    },
    {
      "source": "yield_tokyo"
    },
    {
      "source": "yield_tokyo"
    },
    {
      "source": "yield_tokyo"
    },
    {
      "source": "yield_tokyo"
    },
    {
      "source": "yield_fukuoka"
    },
    {
      "source": "yield_fukuoka"
    },
    {
      "source": "yield_fukuoka"
    },
    {
      "source": "yield_fukuoka"
    },
    {
      "source": "yield_fukuoka"
    },
    {
      "source": "yield_fukuoka"
    },
    {
      "source": "yield_fukuoka"
    },
    {
      "source": "yield_fukuoka"
    },
    {
      "source": "yield_fukuoka"
    }
  ],
  "flagged_count": 0,
  "flagged_by_city": {},
  "report_url": "https://ymatz28-beep.github.io/property-report/"
}
